LabD2/src/LED.v
module LED_ctrl (
    input  wire        clk,       // input clock
    input  wire        start,     // start signal, rising edge valid
    input  wire [7:0]  I0, I1, I2, I3, I4, I5, I6, I7, // parallel input 8x8=64bit
    output wire        clk_LED,   // serial output clock
    output reg         o_LED,     // serial output data
    output reg         clr_LED,   // clear signal, high for 1 clk after start
    output reg         EN_LED     // enable signal, high during transmission
);
    reg [63:0] data_reg;
    reg [5:0]  bit_cnt;
    reg        sending;
    reg        start_d;
    reg        clr_flag;

    initial begin
        data_reg = 0;
        bit_cnt  = 0;
        sending  = 0;
        start_d  = 0;
        clr_flag = 0;
        clr_LED = 1;
        EN_LED = 1;
        o_LED = 0;
    end

    // Combine all inputs into a 64bit data, I7[7] is the highest bit, I0[0] is the lowest.
    wire [63:0] parallel_data = {I7, I6, I5, I4, I3, I2, I1, I0};

    // Detect rising edge of start
    always @(posedge clk) begin
        start_d <= start;
    end

    wire start_rise = (start == 1'b1) && (start_d == 1'b0);

    always @(posedge clk) begin
        if (!sending) begin
            if (start_rise) begin
                clr_LED  <= 1'b1;           // assert clear signal for one cycle
                clr_flag <= 1'b1;           // flag to enter sending state next cycle
                data_reg <= parallel_data;
                bit_cnt  <= 6'd0;
                sending  <= 1'b0;           // wait for clr to finish
                EN_LED   <= 1'b1;
                o_LED    <= 1'b0;
            end else begin
                clr_LED  <= 1'b1;
                EN_LED   <= 1'b1;
                o_LED    <= 1'b0;
            end
        end else begin
            clr_LED  <= 1'b1;                 // clear only lasts one cycle
            EN_LED   <= 1'b1;
            
            if (bit_cnt < 6'd63) begin
                o_LED    <= data_reg[63 - bit_cnt - 1]; // output from high bit to low bit
                bit_cnt  <= bit_cnt + 1'b1;
            end else begin
                bit_cnt  <= 0;
                sending  <= 1'b0;
                EN_LED   <= 1'b1;
            end
        end

        // if clr asserted, move to sending state next cycle
        if (clr_flag) begin
            clr_flag <= 1'b0;
            sending  <= 1'b1;
            o_LED <= data_reg[63];
        end
    end

    assign clk_LED = ~clk & sending;

endmodule

LabD/src/MyMC14495.v
module MyMC14495 (
    input wire D0, D1, D2, D3,
    input wire LE, point,
    output wire a, b, c, d, e, f, g, p
);

    assign D0n = ~D0;
    assign D1n = ~D1;
    assign D2n = ~D2;
    assign D3n = ~D3;

    assign a = LE | ((D3n & D2n & D1n & D0) | (D3n & D2 & D1n & D0n) | (D3 & D2n & D1 & D0) | (D3 & D2 & D1n & D0));
    assign b = LE | ((D3n & D2 & D1n & D0) | (D2 & D1 & D0n) | (D3 & D2 & D0n) | (D3 & D1 & D0));
    assign c = LE | ((D3n & D2n & D1 & D0n) | (D3 & D2 & D0n) | (D3 & D2 & D1));
    assign d = LE | ((D3n & D2n & D1n & D0) | (D3n & D2 & D1n & D0n) | (D2 & D1 & D0) | (D3 & D2n & D1 & D0n));
    assign e = LE | ((D3n & D0) | (D3n & D2 & D1n) | (D2n & D1n & D0));
    assign f = LE | ((D3n & D2n & D0) | (D3n & D2n & D1) | (D3n & D1 & D0) | (D3 & D2 & D1n & D0));
    assign g = LE | ((D3n & D2n & D1n) | (D3n & D2 & D1 & D0) | (D3 & D2 & D1n & D0n));

    assign p = ~point;
endmodule

LabD2/src/createnumber.v
module pbdebounce (
    input wire clk_1ms,
    input wire I,
    output reg O
);
    reg [7 : 0] pbshift;
    initial begin
        O = 0;
    end
    always @(posedge clk_1ms) begin
        pbshift = pbshift << 1;
        pbshift[0] = I;
        if(pbshift == 8'h00) O = 0;
        if(pbshift == 8'hFF) O = 1;
    end
endmodule

module create_number (
    input wire clk,
    input wire [3 : 0] btn,
    output reg [3 : 0] n0, n1, n2, n3
);
    

    wire [3 : 0] t0, t1, t2, t3;

    assign t0 = n0 + 1'b1;
    assign t1 = n1 + 1'b1;
    assign t2 = n2 + 1'b1;
    assign t3 = n3 + 1'b1;

    wire [3 : 0] tbtn;

    
    initial begin
        {n3, n2, n1, n0} <= 16'b0000000000000000;
    end
    pbdebounce db0(.clk_1ms(clk), .I(btn[0]), .O(tbtn[0]));
    pbdebounce db1(.clk_1ms(clk), .I(btn[1]), .O(tbtn[1]));
    pbdebounce db2(.clk_1ms(clk), .I(btn[2]), .O(tbtn[2]));
    pbdebounce db3(.clk_1ms(clk), .I(btn[3]), .O(tbtn[3]));
    
    always @(posedge tbtn[0]) n0 <= t0; 
    always @(posedge tbtn[1]) n1 <= t1; 
    always @(posedge tbtn[2]) n2 <= t2; 
    always @(posedge tbtn[3]) n3 <= t3; 
    
endmodule

LabE/src/clkdiv.v
module clkdiv (
    input wire clk, rst,
    output reg [31 : 0] clkdiv
);

    initial begin
        clkdiv <= 0;
    end
    
    always @(posedge clk or posedge rst) begin
        if(rst) clkdiv <= 0;
        else clkdiv <= clkdiv + 1'b1;
    end

endmodule

LabD2/src/top.v
module top (
    input wire [3 : 0] btn,
    input wire clk,
    input wire [8 : 0] SW,
    output wire [3 : 0] AN,
    output wire [7 : 0] SEGMENT,
    output wire clk_LED, o_LED, clr_LED, EN_LED,
    output wire BTNX4,
    output wire Ring
);
    
    reg GND;
    wire RST;
    initial GND <= 0;
    assign BTNX4 = GND;
    assign RST = GND;
    assign Ring = GND; 

    wire [3 : 0] I0, I1, I2, I3, I4, I5, I6, I7, Hex;
    wire [7 : 0] S0, S1, S2, S3, S4, S5, S6, S7;
    assign Hex = 4'b0000;
    wire [31 : 0] clkd;

    wire P, LE;
    assign P = 0;
    assign LE = 0;
    
    clkdiv cd(.clk(clk), .rst(RST), .clkdiv(clkd));
    create_number numc0(.clk(clkd[17]), .btn(SW[3 : 0]), .n0(I0), .n1(I1), .n2(I2), .n3(I3));
    create_number numc1(.clk(clkd[17]), .btn(SW[7 : 4]), .n0(I4), .n1(I5), .n2(I6), .n3(I7));

    // display_sync ds(.I0(I0), .I1(I1), .I2(I2), .I3(I3), .Hex(Hex), .AN(AN), .scan(clkd[18 : 17]), .points(SW[3 : 0]), .LES(SW[7 : 4]), .p(P), .LE(LE));
    MyMC14495 MyMc(.D0(Hex[0]), .D1(Hex[1]), .D2(Hex[2]), .D3(Hex[3]), .point(P), .LE(LE), 
    .a(SEGMENT[0]), .b(SEGMENT[1]), .c(SEGMENT[2]), .d(SEGMENT[3]), .e(SEGMENT[4]), .f(SEGMENT[5]), .g(SEGMENT[6]), .p(SEGMENT[7]));

    MyMC14495 MyMc0(.D0(I0[0]), .D1(I0[1]), .D2(I0[2]), .D3(I0[3]), .point(SW[0]), .LE(LE), 
    .a(S0[0]), .b(S0[1]), .c(S0[2]), .d(S0[3]), .e(S0[4]), .f(S0[5]), .g(S0[6]), .p(S0[7]));
    MyMC14495 MyMc1(.D0(I1[0]), .D1(I1[1]), .D2(I1[2]), .D3(I1[3]), .point(SW[0]), .LE(LE), 
    .a(S1[0]), .b(S1[1]), .c(S1[2]), .d(S1[3]), .e(S1[4]), .f(S1[5]), .g(S1[6]), .p(S1[7]));
    MyMC14495 MyMc2(.D0(I2[0]), .D1(I2[1]), .D2(I2[2]), .D3(I2[3]), .point(SW[0]), .LE(LE), 
    .a(S2[0]), .b(S2[1]), .c(S2[2]), .d(S2[3]), .e(S2[4]), .f(S2[5]), .g(S2[6]), .p(S2[7]));
    MyMC14495 MyMc3(.D0(I3[0]), .D1(I3[1]), .D2(I3[2]), .D3(I3[3]), .point(SW[0]), .LE(LE), 
    .a(S3[0]), .b(S3[1]), .c(S3[2]), .d(S3[3]), .e(S3[4]), .f(S3[5]), .g(S3[6]), .p(S3[7]));
    MyMC14495 MyMc4(.D0(I4[0]), .D1(I4[1]), .D2(I4[2]), .D3(I4[3]), .point(SW[0]), .LE(LE), 
    .a(S4[0]), .b(S4[1]), .c(S4[2]), .d(S4[3]), .e(S4[4]), .f(S4[5]), .g(S4[6]), .p(S4[7]));
    MyMC14495 MyMc5(.D0(I5[0]), .D1(I5[1]), .D2(I5[2]), .D3(I5[3]), .point(SW[0]), .LE(LE), 
    .a(S5[0]), .b(S5[1]), .c(S5[2]), .d(S5[3]), .e(S5[4]), .f(S5[5]), .g(S5[6]), .p(S5[7]));
    MyMC14495 MyMc6(.D0(I6[0]), .D1(I6[1]), .D2(I6[2]), .D3(I6[3]), .point(SW[0]), .LE(LE), 
    .a(S6[0]), .b(S6[1]), .c(S6[2]), .d(S6[3]), .e(S6[4]), .f(S6[5]), .g(S6[6]), .p(S6[7]));
    MyMC14495 MyMc7(.D0(I7[0]), .D1(I7[1]), .D2(I7[2]), .D3(I7[3]), .point(SW[0]), .LE(LE), 
    .a(S7[0]), .b(S7[1]), .c(S7[2]), .d(S7[3]), .e(S7[4]), .f(S7[5]), .g(S7[6]), .p(S7[7]));

    LED_ctrl ctrl1(.start(SW[8]), .clk(clkd[0]), .I0(S0), .I1(S1), .I2(S2), .I3(S3), .I4(S4), .I5(S5), .I6(S6), .I7(S7), .clk_LED(clk_LED), .o_LED(o_LED), .clr_LED(clr_LED), .EN_LED(EN_LED));
endmodule

LabD2/src/testbench_top.v
`timescale 1ns/1ns

module uut;
    reg [7 : 0] btn;
    reg [8 : 0] SW;
    reg clk;

    wire [3 : 0] AN;
    wire [7 : 0] SEGMENT;
    wire BTNX4;

    initial begin
        btn = 0;
        SW = 9'b000000000;
        clk = 0;
    end

    top uut0(.btn(btn[3 : 0]), .clk(clk), .SW(SW), .AN(AN), .SEGMENT(SEGMENT), .BTNX4(BTNX4));

    always begin
        #5 clk = ~clk;
    end

    initial begin
        #5000 SW[7 : 0] = 8'b00010001;
        #10000 SW[7 : 0] = 8'b00000000;
        #5000 SW[7 : 0] = 8'b00010001;
        #10000 SW[7 : 0] = 8'b00000000;
        #5000 SW[7 : 0] = 8'b01000010;
        #10000 SW[7 : 0] = 8'b00000000;
        #5000 SW[7 : 0] = 8'b00100100;
        #10000 SW[7 : 0] = 8'b00000000;
        #5000 SW[8] = 1;
        #5000 SW[8] = 0;
    end

    initial begin
        $dumpfile(".\\build\\wave.vcd");
        $dumpvars(0, uut);
        #200000 $finish;
    end
    
endmodule

LabD2/build/wave.vcd
$date
	Thu Jun 12 12:31:01 2025
$end
$version
	Icarus Verilog
$end
$timescale
	1ns
$end
$scope module uut $end
$var wire 4 ! AN [3:0] $end
$var wire 8 " SEGMENT [7:0] $end
$var wire 1 # BTNX4 $end
$var reg 9 $ SW [8:0] $end
$var reg 8 % btn [7:0] $end
$var reg 1 & clk $end
$scope module uut0 $end
$var wire 4 ' AN [3:0] $end
$var wire 1 # BTNX4 $end
$var wire 4 ( Hex [3:0] $end
$var wire 1 ) LE $end
$var wire 1 * P $end
$var wire 1 + RST $end
$var wire 1 , Ring $end
$var wire 9 - SW [8:0] $end
$var wire 4 . btn [3:0] $end
$var wire 1 & clk $end
$var wire 1 / o_LED $end
$var wire 1 0 clr_LED $end
$var wire 32 1 clkd [31:0] $end
$var wire 1 2 clk_LED $end
$var wire 8 3 SEGMENT [7:0] $end
$var wire 8 4 S7 [7:0] $end
$var wire 8 5 S6 [7:0] $end
$var wire 8 6 S5 [7:0] $end
$var wire 8 7 S4 [7:0] $end
$var wire 8 8 S3 [7:0] $end
$var wire 8 9 S2 [7:0] $end
$var wire 8 : S1 [7:0] $end
$var wire 8 ; S0 [7:0] $end
$var wire 4 < I7 [3:0] $end
$var wire 4 = I6 [3:0] $end
$var wire 4 > I5 [3:0] $end
$var wire 4 ? I4 [3:0] $end
$var wire 4 @ I3 [3:0] $end
$var wire 4 A I2 [3:0] $end
$var wire 4 B I1 [3:0] $end
$var wire 4 C I0 [3:0] $end
$var wire 1 D EN_LED $end
$var reg 1 E GND $end
$scope module MyMc $end
$var wire 1 F D0 $end
$var wire 1 G D0n $end
$var wire 1 H D1 $end
$var wire 1 I D1n $end
$var wire 1 J D2 $end
$var wire 1 K D2n $end
$var wire 1 L D3 $end
$var wire 1 M D3n $end
$var wire 1 ) LE $end
$var wire 1 N a $end
$var wire 1 O b $end
$var wire 1 P c $end
$var wire 1 Q d $end
$var wire 1 R e $end
$var wire 1 S f $end
$var wire 1 T g $end
$var wire 1 U p $end
$var wire 1 * point $end
$upscope $end
$scope module MyMc0 $end
$var wire 1 V D0 $end
$var wire 1 W D0n $end
$var wire 1 X D1 $end
$var wire 1 Y D1n $end
$var wire 1 Z D2 $end
$var wire 1 [ D2n $end
$var wire 1 \ D3 $end
$var wire 1 ] D3n $end
$var wire 1 ) LE $end
$var wire 1 ^ a $end
$var wire 1 _ b $end
$var wire 1 ` c $end
$var wire 1 a d $end
$var wire 1 b e $end
$var wire 1 c f $end
$var wire 1 d g $end
$var wire 1 e p $end
$var wire 1 f point $end
$upscope $end
$scope module MyMc1 $end
$var wire 1 g D0 $end
$var wire 1 h D0n $end
$var wire 1 i D1 $end
$var wire 1 j D1n $end
$var wire 1 k D2 $end
$var wire 1 l D2n $end
$var wire 1 m D3 $end
$var wire 1 n D3n $end
$var wire 1 ) LE $end
$var wire 1 o a $end
$var wire 1 p b $end
$var wire 1 q c $end
$var wire 1 r d $end
$var wire 1 s e $end
$var wire 1 t f $end
$var wire 1 u g $end
$var wire 1 v p $end
$var wire 1 w point $end
$upscope $end
$scope module MyMc2 $end
$var wire 1 x D0 $end
$var wire 1 y D0n $end
$var wire 1 z D1 $end
$var wire 1 { D1n $end
$var wire 1 | D2 $end
$var wire 1 } D2n $end
$var wire 1 ~ D3 $end
$var wire 1 !" D3n $end
$var wire 1 ) LE $end
$var wire 1 "" a $end
$var wire 1 #" b $end
$var wire 1 $" c $end
$var wire 1 %" d $end
$var wire 1 &" e $end
$var wire 1 '" f $end
$var wire 1 (" g $end
$var wire 1 )" p $end
$var wire 1 *" point $end
$upscope $end
$scope module MyMc3 $end
$var wire 1 +" D0 $end
$var wire 1 ," D0n $end
$var wire 1 -" D1 $end
$var wire 1 ." D1n $end
$var wire 1 /" D2 $end
$var wire 1 0" D2n $end
$var wire 1 1" D3 $end
$var wire 1 2" D3n $end
$var wire 1 ) LE $end
$var wire 1 3" a $end
$var wire 1 4" b $end
$var wire 1 5" c $end
$var wire 1 6" d $end
$var wire 1 7" e $end
$var wire 1 8" f $end
$var wire 1 9" g $end
$var wire 1 :" p $end
$var wire 1 ;" point $end
$upscope $end
$scope module MyMc4 $end
$var wire 1 <" D0 $end
$var wire 1 =" D0n $end
$var wire 1 >" D1 $end
$var wire 1 ?" D1n $end
$var wire 1 @" D2 $end
$var wire 1 A" D2n $end
$var wire 1 B" D3 $end
$var wire 1 C" D3n $end
$var wire 1 ) LE $end
$var wire 1 D" a $end
$var wire 1 E" b $end
$var wire 1 F" c $end
$var wire 1 G" d $end
$var wire 1 H" e $end
$var wire 1 I" f $end
$var wire 1 J" g $end
$var wire 1 K" p $end
$var wire 1 L" point $end
$upscope $end
$scope module MyMc5 $end
$var wire 1 M" D0 $end
$var wire 1 N" D0n $end
$var wire 1 O" D1 $end
$var wire 1 P" D1n $end
$var wire 1 Q" D2 $end
$var wire 1 R" D2n $end
$var wire 1 S" D3 $end
$var wire 1 T" D3n $end
$var wire 1 ) LE $end
$var wire 1 U" a $end
$var wire 1 V" b $end
$var wire 1 W" c $end
$var wire 1 X" d $end
$var wire 1 Y" e $end
$var wire 1 Z" f $end
$var wire 1 [" g $end
$var wire 1 \" p $end
$var wire 1 ]" point $end
$upscope $end
$scope module MyMc6 $end
$var wire 1 ^" D0 $end
$var wire 1 _" D0n $end
$var wire 1 `" D1 $end
$var wire 1 a" D1n $end
$var wire 1 b" D2 $end
$var wire 1 c" D2n $end
$var wire 1 d" D3 $end
$var wire 1 e" D3n $end
$var wire 1 ) LE $end
$var wire 1 f" a $end
$var wire 1 g" b $end
$var wire 1 h" c $end
$var wire 1 i" d $end
$var wire 1 j" e $end
$var wire 1 k" f $end
$var wire 1 l" g $end
$var wire 1 m" p $end
$var wire 1 n" point $end
$upscope $end
$scope module MyMc7 $end
$var wire 1 o" D0 $end
$var wire 1 p" D0n $end
$var wire 1 q" D1 $end
$var wire 1 r" D1n $end
$var wire 1 s" D2 $end
$var wire 1 t" D2n $end
$var wire 1 u" D3 $end
$var wire 1 v" D3n $end
$var wire 1 ) LE $end
$var wire 1 w" a $end
$var wire 1 x" b $end
$var wire 1 y" c $end
$var wire 1 z" d $end
$var wire 1 {" e $end
$var wire 1 |" f $end
$var wire 1 }" g $end
$var wire 1 ~" p $end
$var wire 1 !# point $end
$upscope $end
$scope module cd $end
$var wire 1 & clk $end
$var wire 1 + rst $end
$var reg 32 "# clkdiv [31:0] $end
$upscope $end
$scope module ctrl1 $end
$var wire 8 ## I0 [7:0] $end
$var wire 8 $# I1 [7:0] $end
$var wire 8 %# I2 [7:0] $end
$var wire 8 &# I3 [7:0] $end
$var wire 8 '# I4 [7:0] $end
$var wire 8 (# I5 [7:0] $end
$var wire 8 )# I6 [7:0] $end
$var wire 8 *# I7 [7:0] $end
$var wire 1 +# clk $end
$var wire 1 2 clk_LED $end
$var wire 1 ,# start $end
$var wire 1 -# start_rise $end
$var wire 64 .# parallel_data [63:0] $end
$var reg 1 D EN_LED $end
$var reg 6 /# bit_cnt [5:0] $end
$var reg 1 0 clr_LED $end
$var reg 1 0# clr_flag $end
$var reg 64 1# data_reg [63:0] $end
$var reg 1 / o_LED $end
$var reg 1 2# sending $end
$var reg 1 3# start_d $end
$upscope $end
$scope module numc0 $end
$var wire 4 4# btn [3:0] $end
$var wire 1 5# clk $end
$var wire 4 6# tbtn [3:0] $end
$var wire 4 7# t3 [3:0] $end
$var wire 4 8# t2 [3:0] $end
$var wire 4 9# t1 [3:0] $end
$var wire 4 :# t0 [3:0] $end
$var reg 4 ;# n0 [3:0] $end
$var reg 4 <# n1 [3:0] $end
$var reg 4 =# n2 [3:0] $end
$var reg 4 ># n3 [3:0] $end
$scope module db0 $end
$var wire 1 ?# I $end
$var wire 1 5# clk_1ms $end
$var reg 1 @# O $end
$var reg 8 A# pbshift [7:0] $end
$upscope $end
$scope module db1 $end
$var wire 1 B# I $end
$var wire 1 5# clk_1ms $end
$var reg 1 C# O $end
$var reg 8 D# pbshift [7:0] $end
$upscope $end
$scope module db2 $end
$var wire 1 E# I $end
$var wire 1 5# clk_1ms $end
$var reg 1 F# O $end
$var reg 8 G# pbshift [7:0] $end
$upscope $end
$scope module db3 $end
$var wire 1 H# I $end
$var wire 1 5# clk_1ms $end
$var reg 1 I# O $end
$var reg 8 J# pbshift [7:0] $end
$upscope $end
$upscope $end
$scope module numc1 $end
$var wire 4 K# btn [3:0] $end
$var wire 1 L# clk $end
$var wire 4 M# tbtn [3:0] $end
$var wire 4 N# t3 [3:0] $end
$var wire 4 O# t2 [3:0] $end
$var wire 4 P# t1 [3:0] $end
$var wire 4 Q# t0 [3:0] $end
$var reg 4 R# n0 [3:0] $end
$var reg 4 S# n1 [3:0] $end
$var reg 4 T# n2 [3:0] $end
$var reg 4 U# n3 [3:0] $end
$scope module db0 $end
$var wire 1 V# I $end
$var wire 1 L# clk_1ms $end
$var reg 1 W# O $end
$var reg 8 X# pbshift [7:0] $end
$upscope $end
$scope module db1 $end
$var wire 1 Y# I $end
$var wire 1 L# clk_1ms $end
$var reg 1 Z# O $end
$var reg 8 [# pbshift [7:0] $end
$upscope $end
$scope module db2 $end
$var wire 1 \# I $end
$var wire 1 L# clk_1ms $end
$var reg 1 ]# O $end
$var reg 8 ^# pbshift [7:0] $end
$upscope $end
$scope module db3 $end
$var wire 1 _# I $end
$var wire 1 L# clk_1ms $end
$var reg 1 `# O $end
$var reg 8 a# pbshift [7:0] $end
$upscope $end
$upscope $end
$upscope $end
$upscope $end
$enddefinitions $end
#0
$dumpvars
bx a#
0`#
0_#
bx ^#
0]#
0\#
bx [#
0Z#
0Y#
bx X#
0W#
0V#
b0 U#
b0 T#
b0 S#
b0 R#
b1 Q#
b1 P#
b1 O#
b1 N#
b0 M#
0L#
b0 K#
bx J#
0I#
0H#
bx G#
0F#
0E#
bx D#
0C#
0B#
bx A#
0@#
0?#
b0 >#
b0 =#
b0 <#
b0 ;#
b1 :#
b1 9#
b1 8#
b1 7#
b0 6#
05#
b0 4#
03#
02#
b0 1#
00#
b0 /#
b1100000011000000110000001100000011000000110000001100000011000000 .#
0-#
0,#
0+#
b11000000 *#
b11000000 )#
b11000000 (#
b11000000 '#
b11000000 &#
b11000000 %#
b11000000 $#
b11000000 ##
b0 "#
0!#
1~"
1}"
0|"
0{"
0z"
0y"
0x"
0w"
1v"
0u"
1t"
0s"
1r"
0q"
1p"
0o"
0n"
1m"
1l"
0k"
0j"
0i"
0h"
0g"
0f"
1e"
0d"
1c"
0b"
1a"
0`"
1_"
0^"
0]"
1\"
1["
0Z"
0Y"
0X"
0W"
0V"
0U"
1T"
0S"
1R"
0Q"
1P"
0O"
1N"
0M"
0L"
1K"
1J"
0I"
0H"
0G"
0F"
0E"
0D"
1C"
0B"
1A"
0@"
1?"
0>"
1="
0<"
0;"
1:"
19"
08"
07"
06"
05"
04"
03"
12"
01"
10"
0/"
1."
0-"
1,"
0+"
0*"
1)"
1("
0'"
0&"
0%"
0$"
0#"
0""
1!"
0~
1}
0|
1{
0z
1y
0x
0w
1v
1u
0t
0s
0r
0q
0p
0o
1n
0m
1l
0k
1j
0i
1h
0g
0f
1e
1d
0c
0b
0a
0`
0_
0^
1]
0\
1[
0Z
1Y
0X
1W
0V
1U
1T
0S
0R
0Q
0P
0O
0N
1M
0L
1K
0J
1I
0H
1G
0F
0E
1D
b0 C
b0 B
b0 A
b0 @
b0 ?
b0 >
b0 =
b0 <
b11000000 ;
b11000000 :
b11000000 9
b11000000 8
b11000000 7
b11000000 6
b11000000 5
b11000000 4
b11000000 3
02
b0 1
10
0/
b0 .
b0 -
0,
0+
0*
0)
b0 (
bz '
0&
b0 %
b0 $
0#
b11000000 "
bz !
$end
#5
1+#
b1 1
b1 "#
1&
#10
0&
#15
0+#
b10 1
b10 "#
1&
#20
0&
#25
1+#
b11 1
b11 "#
1&
#30
0&
#35
0+#
b100 1
b100 "#
1&
#40
0&
#45
1+#
b101 1
b101 "#
1&
#50
0&
#55
0+#
b110 1
b110 "#
1&
#60
0&
#65
1+#
b111 1
b111 "#
1&
#70
0&
#75
bx0 X#
bx0 [#
bx0 ^#
bx0 a#
bx0 A#
bx0 D#
bx0 G#
bx0 J#
0+#
1L#
15#
b1000 1
b1000 "#
1&
#80
0&
#85
1+#
b1001 1
b1001 "#
1&
#90
0&
#95
0+#
b1010 1
b1010 "#
1&
#100
0&
#105
1+#
b1011 1
b1011 "#
1&
#110
0&
#115
0+#
b1100 1
b1100 "#
1&
#120
0&
#125
1+#
b1101 1
b1101 "#
1&
#130
0&
#135
0+#
b1110 1
b1110 "#
1&
#140
0&
#145
1+#
b1111 1
b1111 "#
1&
#150
0&
#155
0+#
0L#
05#
b10000 1
b10000 "#
1&
#160
0&
#165
1+#
b10001 1
b10001 "#
1&
#170
0&
#175
0+#
b10010 1
b10010 "#
1&
#180
0&
#185
1+#
b10011 1
b10011 "#
1&
#190
0&
#195
0+#
b10100 1
b10100 "#
1&
#200
0&
#205
1+#
b10101 1
b10101 "#
1&
#210
0&
#215
0+#
b10110 1
b10110 "#
1&
#220
0&
#225
1+#
b10111 1
b10111 "#
1&
#230
0&
#235
bx00 a#
bx00 ^#
bx00 [#
bx00 X#
bx00 J#
bx00 G#
bx00 D#
bx00 A#
0+#
1L#
15#
b11000 1
b11000 "#
1&
#240
0&
#245
1+#
b11001 1
b11001 "#
1&
#250
0&
#255
0+#
b11010 1
b11010 "#
1&
#260
0&
#265
1+#
b11011 1
b11011 "#
1&
#270
0&
#275
0+#
b11100 1
b11100 "#
1&
#280
0&
#285
1+#
b11101 1
b11101 "#
1&
#290
0&
#295
0+#
b11110 1
b11110 "#
1&
#300
0&
#305
1+#
b11111 1
b11111 "#
1&
#310
0&
#315
0+#
0L#
05#
b100000 1
b100000 "#
1&
#320
0&
#325
1+#
b100001 1
b100001 "#
1&
#330
0&
#335
0+#
b100010 1
b100010 "#
1&
#340
0&
#345
1+#
b100011 1
b100011 "#
1&
#350
0&
#355
0+#
b100100 1
b100100 "#
1&
#360
0&
#365
1+#
b100101 1
b100101 "#
1&
#370
0&
#375
0+#
b100110 1
b100110 "#
1&
#380
0&
#385
1+#
b100111 1
b100111 "#
1&
#390
0&
#395
bx000 X#
bx000 [#
bx000 ^#
bx000 a#
bx000 A#
bx000 D#
bx000 G#
bx000 J#
0+#
1L#
15#
b101000 1
b101000 "#
1&
#400
0&
#405
1+#
b101001 1
b101001 "#
1&
#410
0&
#415
0+#
b101010 1
b101010 "#
1&
#420
0&
#425
1+#
b101011 1
b101011 "#
1&
#430
0&
#435
0+#
b101100 1
b101100 "#
1&
#440
0&
#445
1+#
b101101 1
b101101 "#
1&
#450
0&
#455
0+#
b101110 1
b101110 "#
1&
#460
0&
#465
1+#
b101111 1
b101111 "#
1&
#470
0&
#475
0+#
0L#
05#
b110000 1
b110000 "#
1&
#480
0&
#485
1+#
b110001 1
b110001 "#
1&
#490
0&
#495
0+#
b110010 1
b110010 "#
1&
#500
0&
#505
1+#
b110011 1
b110011 "#
1&
#510
0&
#515
0+#
b110100 1
b110100 "#
1&
#520
0&
#525
1+#
b110101 1
b110101 "#
1&
#530
0&
#535
0+#
b110110 1
b110110 "#
1&
#540
0&
#545
1+#
b110111 1
b110111 "#
1&
#550
0&
#555
bx0000 a#
bx0000 ^#
bx0000 [#
bx0000 X#
bx0000 J#
bx0000 G#
bx0000 D#
bx0000 A#
0+#
1L#
15#
b111000 1
b111000 "#
1&
#560
0&
#565
1+#
b111001 1
b111001 "#
1&
#570
0&
#575
0+#
b111010 1
b111010 "#
1&
#580
0&
#585
1+#
b111011 1
b111011 "#
1&
#590
0&
#595
0+#
b111100 1
b111100 "#
1&
#600
0&
#605
1+#
b111101 1
b111101 "#
1&
#610
0&
#615
0+#
b111110 1
b111110 "#
1&
#620
0&
#625
1+#
b111111 1
b111111 "#
1&
#630
0&
#635
0+#
0L#
05#
b1000000 1
b1000000 "#
1&
#640
0&
#645
1+#
b1000001 1
b1000001 "#
1&
#650
0&
#655
0+#
b1000010 1
b1000010 "#
1&
#660
0&
#665
1+#
b1000011 1
b1000011 "#
1&
#670
0&
#675
0+#
b1000100 1
b1000100 "#
1&
#680
0&
#685
1+#
b1000101 1
b1000101 "#
1&
#690
0&
#695
0+#
b1000110 1
b1000110 "#
1&
#700
0&
#705
1+#
b1000111 1
b1000111 "#
1&
#710
0&
#715
bx00000 X#
bx00000 [#
bx00000 ^#
bx00000 a#
bx00000 A#
bx00000 D#
bx00000 G#
bx00000 J#
0+#
1L#
15#
b1001000 1
b1001000 "#
1&
#720
0&
#725
1+#
b1001001 1
b1001001 "#
1&
#730
0&
#735
0+#
b1001010 1
b1001010 "#
1&
#740
0&
#745
1+#
b1001011 1
b1001011 "#
1&
#750
0&
#755
0+#
b1001100 1
b1001100 "#
1&
#760
0&
#765
1+#
b1001101 1
b1001101 "#
1&
#770
0&
#775
0+#
b1001110 1
b1001110 "#
1&
#780
0&
#785
1+#
b1001111 1
b1001111 "#
1&
#790
0&
#795
0+#
0L#
05#
b1010000 1
b1010000 "#
1&
#800
0&
#805
1+#
b1010001 1
b1010001 "#
1&
#810
0&
#815
0+#
b1010010 1
b1010010 "#
1&
#820
0&
#825
1+#
b1010011 1
b1010011 "#
1&
#830
0&
#835
0+#
b1010100 1
b1010100 "#
1&
#840
0&
#845
1+#
b1010101 1
b1010101 "#
1&
#850
0&
#855
0+#
b1010110 1
b1010110 "#
1&
#860
0&
#865
1+#
b1010111 1
b1010111 "#
1&
#870
0&
#875
bx000000 a#
bx000000 ^#
bx000000 [#
bx000000 X#
bx000000 J#
bx000000 G#
bx000000 D#
bx000000 A#
0+#
1L#
15#
b1011000 1
b1011000 "#
1&
#880
0&
#885
1+#
b1011001 1
b1011001 "#
1&
#890
0&
#895
0+#
b1011010 1
b1011010 "#
1&
#900
0&
#905
1+#
b1011011 1
b1011011 "#
1&
#910
0&
#915
0+#
b1011100 1
b1011100 "#
1&
#920
0&
#925
1+#
b1011101 1
b1011101 "#
1&
#930
0&
#935
0+#
b1011110 1
b1011110 "#
1&
#940
0&
#945
1+#
b1011111 1
b1011111 "#
1&
#950
0&
#955
0+#
0L#
05#
b1100000 1
b1100000 "#
1&
#960
0&
#965
1+#
b1100001 1
b1100001 "#
1&
#970
0&
#975
0+#
b1100010 1
b1100010 "#
1&
#980
0&
#985
1+#
b1100011 1
b1100011 "#
1&
#990
0&
#995
0+#
b1100100 1
b1100100 "#
1&
#1000
0&
#1005
1+#
b1100101 1
b1100101 "#
1&
#1010
0&
#1015
0+#
b1100110 1
b1100110 "#
1&
#1020
0&
#1025
1+#
b1100111 1
b1100111 "#
1&
#1030
0&
#1035
bx0000000 X#
bx0000000 [#
bx0000000 ^#
bx0000000 a#
bx0000000 A#
bx0000000 D#
bx0000000 G#
bx0000000 J#
0+#
1L#
15#
b1101000 1
b1101000 "#
1&
#1040
0&
#1045
1+#
b1101001 1
b1101001 "#
1&
#1050
0&
#1055
0+#
b1101010 1
b1101010 "#
1&
#1060
0&
#1065
1+#
b1101011 1
b1101011 "#
1&
#1070
0&
#1075
0+#
b1101100 1
b1101100 "#
1&
#1080
0&
#1085
1+#
b1101101 1
b1101101 "#
1&
#1090
0&
#1095
0+#
b1101110 1
b1101110 "#
1&
#1100
0&
#1105
1+#
b1101111 1
b1101111 "#
1&
#1110
0&
#1115
0+#
0L#
05#
b1110000 1
b1110000 "#
1&
#1120
0&
#1125
1+#
b1110001 1
b1110001 "#
1&
#1130
0&
#1135
0+#
b1110010 1
b1110010 "#
1&
#1140
0&
#1145
1+#
b1110011 1
b1110011 "#
1&
#1150
0&
#1155
0+#
b1110100 1
b1110100 "#
1&
#1160
0&
#1165
1+#
b1110101 1
b1110101 "#
1&
#1170
0&
